qsave/__init__.py
qsave/asyncio/__init__.py
qsave/asyncio/aio.py
qsave/asyncio/aioquicksave.py
qsave/asyncio/aiosession.py
qsave/io.py
qsave/quicksave.py
qsave/session.py
qsave-1.1.2.dist-info/LICENSE
qsave-1.1.2.dist-info/METADATA
qsave-1.1.2.dist-info/WHEEL
qsave-1.1.2.dist-info/RECORD
