Metadata-Version: 2.3
Name: qsave
Version: 1.1.2
Summary: QuickSave is a fast, memory-efficient, and lightweight key-value database.
License: MIT
Keywords: jsondb,quicksave,key-value,database,lightweight,memory-efficient,json
Author: Nasrollah Yusefi nasrollahyusefi2004@gmail.com
Requires-Python: >=3.7,<4.0
Classifier: License :: OSI Approved :: MIT License
Classifier: Programming Language :: Python :: 3
Classifier: Programming Language :: Python :: 3.7
Classifier: Programming Language :: Python :: 3.8
Classifier: Programming Language :: Python :: 3.9
Classifier: Programming Language :: Python :: 3.10
Classifier: Programming Language :: Python :: 3.11
Classifier: Programming Language :: Python :: 3.12
Classifier: Programming Language :: Python :: 3.13
Provides-Extra: async
Requires-Dist: aiofiles (>=23.1.0,<24.0.0) ; extra == "async"
Project-URL: Documentation, https://nasrollahyusefi.github.io/QuickSave/
Project-URL: Homepage, https://github.com/NasrollahYusefi/QuickSave
